artefacts/__init__.py
artefacts/api/__init__.py
artefacts/api/client.py
artefacts/api/errors.py
artefacts/api/types.py
artefacts/api/api/__init__.py
artefacts/api/api/default/__init__.py
artefacts/api/api/default/get_artifact.py
artefacts/api/api/job/__init__.py
artefacts/api/api/job/api_project_new_job.py
artefacts/api/api/job/get_artifact_downloads.py
artefacts/api/api/job/get_job_by_commit.py
artefacts/api/api/job/get_job_test_results.py
artefacts/api/api/job/post_update_job_results.py
artefacts/api/api/job/put_update_job_results.py
artefacts/api/api/project/__init__.py
artefacts/api/api/project/api_project_info.py
artefacts/api/api/project/create_remote.py
artefacts/api/api/project/get_badge.py
artefacts/api/api/project/get_config.py
artefacts/api/api/project/get_last_jobs.py
artefacts/api/api/project/upload_source.py
artefacts/api/api/run/__init__.py
artefacts/api/api/run/create_job_run.py
artefacts/api/api/run/submit_run_results.py
artefacts/api/models/__init__.py
artefacts/api/models/artifact_response.py
artefacts/api/models/create_new_job.py
artefacts/api/models/create_remote.py
artefacts/api/models/create_remote_response.py
artefacts/api/models/create_remote_response_upload_urls.py
artefacts/api/models/error.py
artefacts/api/models/error_errors.py
artefacts/api/models/get_artifact_downloads_response.py
artefacts/api/models/job.py
artefacts/api/models/last_jobs_response.py
artefacts/api/models/presigned_url.py
artefacts/api/models/presigned_url_fields.py
artefacts/api/models/project.py
artefacts/api/models/register_run.py
artefacts/api/models/register_run_tests_item.py
artefacts/api/models/scenario_map_response.py
artefacts/api/models/submit_run_results.py
artefacts/api/models/submit_run_results_metrics.py
artefacts/api/models/submit_run_results_response.py
artefacts/api/models/submit_run_results_response_upload_urls.py
artefacts/api/models/submit_run_results_tests_item.py
artefacts/api/models/submit_run_results_uploads.py
artefacts_cli-0.12.0.dist-info/METADATA
artefacts_cli-0.12.0.dist-info/WHEEL
artefacts_cli-0.12.0.dist-info/entry_points.txt
artefacts_cli-0.12.0.dist-info/top_level.txt
artefacts_cli-0.12.0.dist-info/RECORD
