Metadata-Version: 2.4
Name: artefacts_cli
Version: 0.12.0
Author-email: FD <fabian@artefacts.com>, AGC <alejandro@artefacts.com>, TN <tomo@artefacts.com>, EP <eric@artefacts.com>
License-Expression: Apache-2.0
Project-URL: Homepage, https://github.com/art-e-fact/artefacts-client
Project-URL: Bug Tracker, https://github.com/art-e-fact/artefacts-client/issues
Project-URL: Changelog, https://github.com/art-e-fact/artefacts-client/CHANGELOG.md
Classifier: Programming Language :: Python :: 3
Classifier: Operating System :: OS Independent
Requires-Python: >=3.10
Requires-Dist: artefacts-c2d>=1.7.1
Requires-Dist: artefacts-copava>=0.1.15
Requires-Dist: artefacts-click
Requires-Dist: artefacts-xray>=0.2.0
Requires-Dist: docker==7.1.0
Requires-Dist: gitignore_parser>=0.1.11
Requires-Dist: junitparser>=2.5
Requires-Dist: mcap
Requires-Dist: mcap-ros2-support
Requires-Dist: psutil==7.0.0
Requires-Dist: PyYAML>=6.0
Requires-Dist: requests>=2.27.1
Requires-Dist: rospkg
Requires-Dist: semver==3.0.4
Requires-Dist: urllib3>=2.4.0
Requires-Dist: attrs>=21.3.0
Requires-Dist: httpx
Requires-Dist: httpx_retries
Provides-Extra: dev
Requires-Dist: awscli; extra == "dev"
Requires-Dist: babel==2.17.0; extra == "dev"
Requires-Dist: build; extra == "dev"
Requires-Dist: lark; extra == "dev"
Requires-Dist: mkdocs-click==0.8.0; extra == "dev"
Requires-Dist: mkdocs-material==8.5.6; extra == "dev"
Requires-Dist: mkdocs-mermaid2-plugin==0.6.0; extra == "dev"
Requires-Dist: mkdocs==1.4.2; extra == "dev"
Requires-Dist: pre-commit; extra == "dev"
Requires-Dist: pyre-check; extra == "dev"
Requires-Dist: pytest; extra == "dev"
Requires-Dist: pytest-cov; extra == "dev"
Requires-Dist: pytest-env; extra == "dev"
Requires-Dist: pytest-mock; extra == "dev"
Requires-Dist: python-markdown-math; extra == "dev"
Requires-Dist: ruff>=0.9.2; extra == "dev"
Requires-Dist: setuptools_scm>=8; extra == "dev"
Requires-Dist: twine; extra == "dev"
Provides-Extra: dev-extended
Requires-Dist: artefacts_cli[dev]; extra == "dev-extended"
Requires-Dist: pytest-watch; extra == "dev-extended"
